clproc/__init__.py
clproc/cli.py
clproc/core.py
clproc/discovery.py
clproc/exc.py
clproc/model.py
clproc/py.typed
clproc/reporting.py
clproc/textprocessing.py
clproc/parser/__init__.py
clproc/parser/core.py
clproc/parser/v1.py
clproc/parser/v2.py
clproc/renderer/__init__.py
clproc/renderer/base.py
clproc/renderer/json.py
clproc/renderer/markdown.py
clproc-2024.8.12.dist-info/LICENSE
clproc-2024.8.12.dist-info/METADATA
clproc-2024.8.12.dist-info/WHEEL
clproc-2024.8.12.dist-info/entry_points.txt
clproc-2024.8.12.dist-info/top_level.txt
clproc-2024.8.12.dist-info/RECORD
