Metadata-Version: 2.1
Name: clproc
Version: 2024.8.12
Summary: Generate curated changelogs into various formats.
Author-email: Michel Albert <michel.albert@post.lu>
License: MIT License
Project-URL: Source, https://github.com/post-luxembourg/clproc
Project-URL: Issues, https://github.com/post-luxembourg/clproc/issues
Keywords: changelog,documentation,json,markdown,pre-commit,release notes,yaml
Classifier: Development Status :: 5 - Production/Stable
Classifier: Environment :: Console
Classifier: Intended Audience :: Developers
Classifier: License :: OSI Approved :: MIT License
Classifier: Operating System :: OS Independent
Classifier: Topic :: Documentation
Classifier: Topic :: Software Development :: Documentation
Classifier: Topic :: Utilities
Requires-Python: >=3.7
License-File: LICENSE
Requires-Dist: packaging
Requires-Dist: python-dateutil
Requires-Dist: pyyaml
Requires-Dist: tomli
Provides-Extra: dev
Requires-Dist: furo ; extra == 'dev'
Requires-Dist: mypy ; extra == 'dev'
Requires-Dist: myst-parser ; extra == 'dev'
Requires-Dist: sphinx ; extra == 'dev'
Requires-Dist: sphinx-rtd-theme ; extra == 'dev'
Requires-Dist: types-PyYAML ; extra == 'dev'
Requires-Dist: types-python-dateutil ; extra == 'dev'
Provides-Extra: test
Requires-Dist: pytest ; extra == 'test'
Requires-Dist: pytest-cache ; extra == 'test'
Requires-Dist: pytest-coverage ; extra == 'test'
